setup.py
txetcd/__init__.py
txetcd/client.py
txetcd/locking.py
txetcd.egg-info/PKG-INFO
txetcd.egg-info/SOURCES.txt
txetcd.egg-info/dependency_links.txt
txetcd.egg-info/requires.txt
txetcd.egg-info/top_level.txt