Metadata-Version: 1.0
Name: txetcd
Version: 0.1-dev
Summary: A Twisted client for etcd: https://github.com/coreos/etcd
Home-page: https://github.com/russellhaering/txetcd
Author: Russell Haering
Author-email: russellhaering@gmail.com
License: Apache License (2.0)
Platform: UNKNOWN
